MANIFEST.in
README.rst
requirements.txt
setup.cfg
setup.py
djmicrosip_puntos/__init__.py
djmicrosip_puntos/__init__.pyc
djmicrosip_puntos/config.pyc
djmicrosip_puntos/forms.pyc
djmicrosip_puntos/models.pyc
djmicrosip_puntos/urls.pyc
djmicrosip_puntos/views.pyc
djmicrosip_puntos.egg-info/PKG-INFO
djmicrosip_puntos.egg-info/SOURCES.txt
djmicrosip_puntos.egg-info/dependency_links.txt
djmicrosip_puntos.egg-info/requires.txt
djmicrosip_puntos.egg-info/top_level.txt
djmicrosip_puntos/custom_db/__init__.py
djmicrosip_puntos/custom_db/__init__.pyc
djmicrosip_puntos/custom_db/core/__init__.py
djmicrosip_puntos/custom_db/core/__init__.pyc
djmicrosip_puntos/custom_db/core/procedures.pyc
djmicrosip_puntos/custom_db/core/sql_queries.pyc
djmicrosip_puntos/custom_db/punto_venta/__init__.py
djmicrosip_puntos/custom_db/punto_venta/__init__.pyc
djmicrosip_puntos/custom_db/punto_venta/procedures.pyc
djmicrosip_puntos/custom_db/punto_venta/report_builder.py
djmicrosip_puntos/custom_db/punto_venta/report_builder.pyc
djmicrosip_puntos/custom_db/punto_venta/sql_queries.pyc
djmicrosip_puntos/custom_db/ventas/__init__.py
djmicrosip_puntos/custom_db/ventas/__init__.pyc
djmicrosip_puntos/custom_db/ventas/procedures.pyc
djmicrosip_puntos/custom_db/ventas/sql_queries.pyc
djmicrosip_puntos/static/DINERO CLIENTE.rtm
djmicrosip_puntos/static/DINERO ELECTRONICO CLIENTE (porcentaje fijo).rtm
djmicrosip_puntos/static/DINERO ELECTRONICO CLIENTE 2.rtm
djmicrosip_puntos/static/DINERO ELECTRONICO CLIENTE.rtm
djmicrosip_puntos/static/DINERO ELECTRONICO.rtm
djmicrosip_puntos/static/DINERO.rtm
djmicrosip_puntos/templates/djmicrosip_puntos/base.html
djmicrosip_puntos/templates/djmicrosip_puntos/index.html
djmicrosip_puntos/templates/djmicrosip_puntos/articulos/articulo.html
djmicrosip_puntos/templates/djmicrosip_puntos/articulos/articulos.html
djmicrosip_puntos/templates/djmicrosip_puntos/articulos/grupo.html
djmicrosip_puntos/templates/djmicrosip_puntos/articulos/grupos.html
djmicrosip_puntos/templates/djmicrosip_puntos/articulos/linea.html
djmicrosip_puntos/templates/djmicrosip_puntos/articulos/lineas.html
djmicrosip_puntos/templates/djmicrosip_puntos/clientes/cliente.html
